{
    "metadata": {
        "dataVersion": "2",
        "matchId": "KR_5181737507",
        "participants": [
            "IXi7FuJ5u400JSEc4AxzfJIOwEocoRh80yfg56oUZrd-E4cvBZVIm_zh8gZpiPYHtOHDIb0dfLyPGA",
            "pI_--VRQdydjgTfuj1v7UCNShT7zaQ0n451pC8D-fS_66pR8vNiS8vWZOAnZk0agBIcvoy1Utj5Utw",
            "96nKM7D0y4_aBUawAzgV_YNJPQOrUd31kZQROgPWGoMbn7mgo5ls_DMngFzkjSN6JLnVLf27Kb3YqA",
            "g7j3oRu9TVaaRwBcqAg8VHLXKYT_1lXJflvaGcS9vS0OOsDOi9iCZjnPuTpKekYpKA9-NDKSpCr_5w",
            "CMOQyxto9pp0_IpgEVHARRSMaytCOBZHm6Bjkkl0xnl5zDQXsOSAt88M7Rnsy5NFL4RwanE6RQYwdg",
            "anhO2QehkXHiEYoLJ35K2C3cRI_8P3IhxcQd5RPR60ZvjNSOAs8jAy2Ou53oNzoVuqbrmipMcTZsOw",
            "k2Gcv83OOAUzNH9ZbvyWFEaQJi1GPQRRfu77RH3v8G41YyujAYTmr6_GbYInhy7g3y0QgUJWkoxkSg",
            "DYsLx6LBCXy2rGkxBHuMVLfpXIFPu9laxRCKQdSHVKpvibW6SjvrPszVg08hVH0YJayl_Q-XxVUWOA",
            "CiqgoKTY6Jb5gmYdo40KpXpH6zA6TunRnAdSvEDcbIJSwGHmCAB-IVyZ83CHIy-udMuVqdiw6Jk8Zw",
            "R4-izM141yZx6eFehD0c9mGIVU_Csyk5Hsj8ITZAT8sarJ9tA7npf1nQ4Kra5yCy4gadj9zR8DToQw"
        ]
    },
    "info": {
        "gameCreation": 1620448343000,
        "gameDuration": 1700419,
        "gameId": 5181737507,
        "gameMode": "CLASSIC",
        "gameName": "teambuilder-match-5181737507",
        "gameStartTimestamp": 1620448371385,
        "gameType": "MATCHED_GAME",
        "gameVersion": "11.9.372.2066",
        "mapId": 11,
        "participants": [
            {
                "assists": 7,
                "baronKills": 0,
                "bountyLevel": 0,
                "champExperience": 15068,
                "champLevel": 16,
                "championId": 84,
                "championName": "Akali",
                "championTransform": 0,
                "consumablesPurchased": 4,
                "damageDealtToBuildings": 3557,
                "damageDealtToObjectives": 3833,
                "damageDealtToTurrets": 3557,
                "damageSelfMitigated": 18681,
                "deaths": 8,
                "detectorWardsPlaced": 2,
                "doubleKills": 0,
                "dragonKills": 0,
                "firstBloodAssist": false,
                "firstBloodKill": false,
                "firstTowerAssist": false,
                "firstTowerKill": true,
                "gameEndedInEarlySurrender": false,
                "gameEndedInSurrender": false,
                "goldEarned": 13150,
                "goldSpent": 13000,
                "individualPosition": "TOP",
                "inhibitorKills": 0,
                "inhibitorsLost": 0,
                "item0": 4633,
                "item1": 1026,
                "item2": 3157,
                "item3": 4637,
                "item4": 4630,
                "item5": 3020,
                "item6": 3363,
                "itemsPurchased": 26,
                "killingSprees": 3,
                "kills": 11,
                "lane": "TOP",
                "largestCriticalStrike": 0,
                "largestKillingSpree": 3,
                "largestMultiKill": 1,
                "longestTimeSpentLiving": 373,
                "magicDamageDealt": 101547,
                "magicDamageDealtToChampions": 21681,
                "magicDamageTaken": 9451,
                "neutralMinionsKilled": 12,
                "nexusKills": 0,
                "nexusLost": 0,
                "objectivesStolen": 0,
                "objectivesStolenAssists": 0,
                "participantId": 1,
                "pentaKills": 0,
                "perks": {
                    "statPerks": {
                        "defense": 5002,
                        "flex": 5008,
                        "offense": 5008
                    },
                    "styles": [
                        {
                            "description": "primaryStyle",
                            "selections": [
                                {
                                    "perk": 8010,
                                    "var1": 633,
                                    "var2": 0,
                                    "var3": 0
                                },
                                {
                                    "perk": 8009,
                                    "var1": 922,
                                    "var2": 0,
                                    "var3": 0
                                },
                                {
                                    "perk": 9105,
                                    "var1": 13,
                                    "var2": 0,
                                    "var3": 0
                                },
                                {
                                    "perk": 8014,
                                    "var1": 454,
                                    "var2": 0,
                                    "var3": 0
                                }
                            ],
                            "style": 8000
                        },
                        {
                            "description": "subStyle",
                            "selections": [
                                {
                                    "perk": 8139,
                                    "var1": 1344,
                                    "var2": 0,
                                    "var3": 0
                                },
                                {
                                    "perk": 8135,
                                    "var1": 0,
                                    "var2": 5,
                                    "var3": 0
                                }
                            ],
                            "style": 8100
                        }
                    ]
                },
                "physicalDamageDealt": 15493,
                "physicalDamageDealtToChampions": 1812,
                "physicalDamageTaken": 21218,
                "profileIcon": 4863,
                "puuid": "IXi7FuJ5u400JSEc4AxzfJIOwEocoRh80yfg56oUZrd-E4cvBZVIm_zh8gZpiPYHtOHDIb0dfLyPGA",
                "quadraKills": 0,
                "riotIdName": "",
                "riotIdTagline": "",
                "role": "SOLO",
                "sightWardsBoughtInGame": 0,
                "spell1Casts": 135,
                "spell2Casts": 31,
                "spell3Casts": 88,
                "spell4Casts": 22,
                "summoner1Casts": 7,
                "summoner1Id": 14,
                "summoner2Casts": 4,
                "summoner2Id": 12,
                "summonerId": "rGXl_Zjv5tx0xAMOcXr2_0Ya4-SvzwuRAj3fVQS9014rg2U",
                "summonerLevel": 77,
                "summonerName": "돼중원돼지훈",
                "teamEarlySurrendered": false,
                "teamId": 100,
                "teamPosition": "TOP",
                "timeCCingOthers": 1,
                "timePlayed": 1698,
                "totalDamageDealt": 122289,
                "totalDamageDealtToChampions": 25035,
                "totalDamageShieldedOnTeammates": 0,
                "totalDamageTaken": 31325,
                "totalHeal": 3634,
                "totalHealsOnTeammates": 0,
                "totalMinionsKilled": 156,
                "totalTimeCCDealt": 59,
                "totalTimeSpentDead": 242,
                "totalUnitsHealed": 1,
                "tripleKills": 0,
                "trueDamageDealt": 5248,
                "trueDamageDealtToChampions": 1541,
                "trueDamageTaken": 656,
                "turretKills": 1,
                "turretsLost": 5,
                "unrealKills": 0,
                "visionScore": 33,
                "visionWardsBoughtInGame": 2,
                "wardsKilled": 2,
                "wardsPlaced": 11,
                "win": true
            },
            {
                "assists": 10,
                "baronKills": 1,
                "bountyLevel": 0,
                "champExperience": 13395,
                "champLevel": 15,
                "championId": 76,
                "championName": "Nidalee",
                "championTransform": 0,
                "consumablesPurchased": 11,
                "damageDealtToBuildings": 1603,
                "damageDealtToObjectives": 14646,
                "damageDealtToTurrets": 1603,
                "damageSelfMitigated": 12921,
                "deaths": 8,
                "detectorWardsPlaced": 8,
                "doubleKills": 1,
                "dragonKills": 1,
                "firstBloodAssist": false,
                "firstBloodKill": true,
                "firstTowerAssist": false,
                "firstTowerKill": false,
                "gameEndedInEarlySurrender": false,
                "gameEndedInSurrender": false,
                "goldEarned": 11185,
                "goldSpent": 10910,
                "individualPosition": "JUNGLE",
                "inhibitorKills": 1,
                "inhibitorsLost": 0,
                "item0": 3020,
                "item1": 1058,
                "item2": 2420,
                "item3": 3100,
                "item4": 4636,
                "item5": 1082,
                "item6": 3364,
                "itemsPurchased": 27,
                "killingSprees": 3,
                "kills": 9,
                "lane": "JUNGLE",
                "largestCriticalStrike": 0,
                "largestKillingSpree": 4,
                "largestMultiKill": 2,
                "longestTimeSpentLiving": 541,
                "magicDamageDealt": 125227,
                "magicDamageDealtToChampions": 14564,
                "magicDamageTaken": 10817,
                "neutralMinionsKilled": 120,
                "nexusKills": 0,
                "nexusLost": 0,
                "objectivesStolen": 0,
                "objectivesStolenAssists": 0,
                "participantId": 2,
                "pentaKills": 0,
                "perks": {
                    "statPerks": {
                        "defense": 5002,
                        "flex": 5008,
                        "offense": 5005
                    },
                    "styles": [
                        {
                            "description": "primaryStyle",
                            "selections": [
                                {
                                    "perk": 8128,
                                    "var1": 1019,
                                    "var2": 17,
                                    "var3": 0
                                },
                                {
                                    "perk": 8143,
                                    "var1": 381,
                                    "var2": 0,
                                    "var3": 0
                                },
                                {
                                    "perk": 8138,
                                    "var1": 30,
                                    "var2": 0,
                                    "var3": 0
                                },
                                {
                                    "perk": 8135,
                                    "var1": 0,
                                    "var2": 5,
                                    "var3": 0
                                }
                            ],
                            "style": 8100
                        },
                        {
                            "description": "subStyle",
                            "selections": [
                                {
                                    "perk": 8232,
                                    "var1": 5,
                                    "var2": 20,
                                    "var3": 0
                                },
                                {
                                    "perk": 8233,
                                    "var1": 19,
                                    "var2": 20,
                                    "var3": 0
                                }
                            ],
                            "style": 8200
                        }
                    ]
                },
                "physicalDamageDealt": 13267,
                "physicalDamageDealtToChampions": 1281,
                "physicalDamageTaken": 18046,
                "profileIcon": 3811,
                "puuid": "pI_--VRQdydjgTfuj1v7UCNShT7zaQ0n451pC8D-fS_66pR8vNiS8vWZOAnZk0agBIcvoy1Utj5Utw",
                "quadraKills": 0,
                "riotIdName": "",
                "riotIdTagline": "",
                "role": "NONE",
                "sightWardsBoughtInGame": 0,
                "spell1Casts": 199,
                "spell2Casts": 257,
                "spell3Casts": 120,
                "spell4Casts": 268,
                "summoner1Casts": 3,
                "summoner1Id": 4,
                "summoner2Casts": 12,
                "summoner2Id": 11,
                "summonerId": "IC9aZSyWxct6UHjwCClrDPxcvyxwmq5brvQ86OcfynMy-is",
                "summonerLevel": 261,
                "summonerName": "YoonTaekyun",
                "teamEarlySurrendered": false,
                "teamId": 100,
                "teamPosition": "JUNGLE",
                "timeCCingOthers": 4,
                "timePlayed": 1698,
                "totalDamageDealt": 145481,
                "totalDamageDealtToChampions": 16078,
                "totalDamageShieldedOnTeammates": 0,
                "totalDamageTaken": 29363,
                "totalHeal": 12427,
                "totalHealsOnTeammates": 1241,
                "totalMinionsKilled": 23,
                "totalTimeCCDealt": 71,
                "totalTimeSpentDead": 207,
                "totalUnitsHealed": 4,
                "tripleKills": 0,
                "trueDamageDealt": 6987,
                "trueDamageDealtToChampions": 233,
                "trueDamageTaken": 500,
                "turretKills": 1,
                "turretsLost": 5,
                "unrealKills": 0,
                "visionScore": 30,
                "visionWardsBoughtInGame": 10,
                "wardsKilled": 4,
                "wardsPlaced": 9,
                "win": true
            },
            {
                "assists": 15,
                "baronKills": 0,
                "bountyLevel": 1,
                "champExperience": 15098,
                "champLevel": 16,
                "championId": 101,
                "championName": "Xerath",
                "championTransform": 0,
                "consumablesPurchased": 5,
                "damageDealtToBuildings": 2828,
                "damageDealtToObjectives": 5755,
                "damageDealtToTurrets": 2828,
                "damageSelfMitigated": 3975,
                "deaths": 6,
                "detectorWardsPlaced": 3,
                "doubleKills": 0,
                "dragonKills": 0,
                "firstBloodAssist": false,
                "firstBloodKill": false,
                "firstTowerAssist": false,
                "firstTowerKill": false,
                "gameEndedInEarlySurrender": false,
                "gameEndedInSurrender": false,
                "goldEarned": 11409,
                "goldSpent": 9525,
                "individualPosition": "MIDDLE",
                "inhibitorKills": 0,
                "inhibitorsLost": 0,
                "item0": 3020,
                "item1": 4628,
                "item2": 1082,
                "item3": 3070,
                "item4": 6655,
                "item5": 1058,
                "item6": 3363,
                "itemsPurchased": 16,
                "killingSprees": 1,
                "kills": 5,
                "lane": "MIDDLE",
                "largestCriticalStrike": 0,
                "largestKillingSpree": 3,
                "largestMultiKill": 1,
                "longestTimeSpentLiving": 443,
                "magicDamageDealt": 127491,
                "magicDamageDealtToChampions": 20904,
                "magicDamageTaken": 5399,
                "neutralMinionsKilled": 5,
                "nexusKills": 0,
                "nexusLost": 0,
                "objectivesStolen": 0,
                "objectivesStolenAssists": 0,
                "participantId": 3,
                "pentaKills": 0,
                "perks": {
                    "statPerks": {
                        "defense": 5002,
                        "flex": 5008,
                        "offense": 5008
                    },
                    "styles": [
                        {
                            "description": "primaryStyle",
                            "selections": [
                                {
                                    "perk": 8229,
                                    "var1": 1425,
                                    "var2": 0,
                                    "var3": 0
                                },
                                {
                                    "perk": 8226,
                                    "var1": 250,
                                    "var2": 1372,
                                    "var3": 0
                                },
                                {
                                    "perk": 8233,
                                    "var1": 19,
                                    "var2": 30,
                                    "var3": 0
                                },
                                {
                                    "perk": 8236,
                                    "var1": 24,
                                    "var2": 0,
                                    "var3": 0
                                }
                            ],
                            "style": 8200
                        },
                        {
                            "description": "subStyle",
                            "selections": [
                                {
                                    "perk": 8304,
                                    "var1": 10,
                                    "var2": 3,
                                    "var3": 0
                                },
                                {
                                    "perk": 8321,
                                    "var1": 5,
                                    "var2": 0,
                                    "var3": 0
                                }
                            ],
                            "style": 8300
                        }
                    ]
                },
                "physicalDamageDealt": 7231,
                "physicalDamageDealtToChampions": 350,
                "physicalDamageTaken": 5838,
                "profileIcon": 3466,
                "puuid": "96nKM7D0y4_aBUawAzgV_YNJPQOrUd31kZQROgPWGoMbn7mgo5ls_DMngFzkjSN6JLnVLf27Kb3YqA",
                "quadraKills": 0,
                "riotIdName": "",
                "riotIdTagline": "",
                "role": "SOLO",
                "sightWardsBoughtInGame": 0,
                "spell1Casts": 105,
                "spell2Casts": 65,
                "spell3Casts": 27,
                "spell4Casts": 42,
                "summoner1Casts": 3,
                "summoner1Id": 12,
                "summoner2Casts": 4,
                "summoner2Id": 4,
                "summonerId": "CFiNtj0jfXtInf6U4GhfWrorzDCN2JvGZtrPN58BasEIv5g",
                "summonerLevel": 210,
                "summonerName": "가와울",
                "teamEarlySurrendered": false,
                "teamId": 100,
                "teamPosition": "MIDDLE",
                "timeCCingOthers": 18,
                "timePlayed": 1698,
                "totalDamageDealt": 136232,
                "totalDamageDealtToChampions": 21255,
                "totalDamageShieldedOnTeammates": 0,
                "totalDamageTaken": 11406,
                "totalHeal": 974,
                "totalHealsOnTeammates": 0,
                "totalMinionsKilled": 188,
                "totalTimeCCDealt": 161,
                "totalTimeSpentDead": 189,
                "totalUnitsHealed": 1,
                "tripleKills": 0,
                "trueDamageDealt": 1510,
                "trueDamageDealtToChampions": 0,
                "trueDamageTaken": 168,
                "turretKills": 2,
                "turretsLost": 5,
                "unrealKills": 0,
                "visionScore": 23,
                "visionWardsBoughtInGame": 3,
                "wardsKilled": 0,
                "wardsPlaced": 12,
                "win": true
            },
            {
                "assists": 10,
                "baronKills": 0,
                "bountyLevel": 0,
                "champExperience": 13945,
                "champLevel": 15,
                "championId": 236,
                "championName": "Lucian",
                "championTransform": 0,
                "consumablesPurchased": 1,
                "damageDealtToBuildings": 7291,
                "damageDealtToObjectives": 21609,
                "damageDealtToTurrets": 7291,
                "damageSelfMitigated": 10575,
                "deaths": 3,
                "detectorWardsPlaced": 0,
                "doubleKills": 0,
                "dragonKills": 1,
                "firstBloodAssist": true,
                "firstBloodKill": false,
                "firstTowerAssist": false,
                "firstTowerKill": false,
                "gameEndedInEarlySurrender": false,
                "gameEndedInSurrender": false,
                "goldEarned": 14858,
                "goldSpent": 13980,
                "individualPosition": "BOTTOM",
                "inhibitorKills": 0,
                "inhibitorsLost": 0,
                "item0": 1055,
                "item1": 6672,
                "item2": 3508,
                "item3": 1001,
                "item4": 3031,
                "item5": 3072,
                "item6": 3363,
                "itemsPurchased": 18,
                "killingSprees": 2,
                "kills": 14,
                "lane": "BOTTOM",
                "largestCriticalStrike": 2331,
                "largestKillingSpree": 9,
                "largestMultiKill": 1,
                "longestTimeSpentLiving": 682,
                "magicDamageDealt": 3348,
                "magicDamageDealtToChampions": 1650,
                "magicDamageTaken": 4235,
                "neutralMinionsKilled": 12,
                "nexusKills": 1,
                "nexusLost": 0,
                "objectivesStolen": 0,
                "objectivesStolenAssists": 0,
                "participantId": 4,
                "pentaKills": 0,
                "perks": {
                    "statPerks": {
                        "defense": 5002,
                        "flex": 5008,
                        "offense": 5005
                    },
                    "styles": [
                        {
                            "description": "primaryStyle",
                            "selections": [
                                {
                                    "perk": 8005,
                                    "var1": 1810,
                                    "var2": 1051,
                                    "var3": 758
                                },
                                {
                                    "perk": 9101,
                                    "var1": 3400,
                                    "var2": 4514,
                                    "var3": 0
                                },
                                {
                                    "perk": 9103,
                                    "var1": 16,
                                    "var2": 30,
                                    "var3": 0
                                },
                                {
                                    "perk": 8017,
                                    "var1": 941,
                                    "var2": 0,
                                    "var3": 0
                                }
                            ],
                            "style": 8000
                        },
                        {
                            "description": "subStyle",
                            "selections": [
                                {
                                    "perk": 8139,
                                    "var1": 742,
                                    "var2": 0,
                                    "var3": 0
                                },
                                {
                                    "perk": 8135,
                                    "var1": 0,
                                    "var2": 5,
                                    "var3": 0
                                }
                            ],
                            "style": 8100
                        }
                    ]
                },
                "physicalDamageDealt": 134281,
                "physicalDamageDealtToChampions": 22660,
                "physicalDamageTaken": 7356,
                "profileIcon": 7,
                "puuid": "g7j3oRu9TVaaRwBcqAg8VHLXKYT_1lXJflvaGcS9vS0OOsDOi9iCZjnPuTpKekYpKA9-NDKSpCr_5w",
                "quadraKills": 0,
                "riotIdName": "",
                "riotIdTagline": "",
                "role": "CARRY",
                "sightWardsBoughtInGame": 0,
                "spell1Casts": 60,
                "spell2Casts": 28,
                "spell3Casts": 35,
                "spell4Casts": 10,
                "summoner1Casts": 3,
                "summoner1Id": 7,
                "summoner2Casts": 4,
                "summoner2Id": 4,
                "summonerId": "5bPLRkaqcNvtXXbHLgvuZXsQQkbpx13l6qyH0jVG8vNcbA",
                "summonerLevel": 322,
                "summonerName": "컴공과 윤테디",
                "teamEarlySurrendered": false,
                "teamId": 100,
                "teamPosition": "BOTTOM",
                "timeCCingOthers": 2,
                "timePlayed": 1698,
                "totalDamageDealt": 150657,
                "totalDamageDealtToChampions": 26854,
                "totalDamageShieldedOnTeammates": 0,
                "totalDamageTaken": 12183,
                "totalHeal": 1697,
                "totalHealsOnTeammates": 513,
                "totalMinionsKilled": 189,
                "totalTimeCCDealt": 47,
                "totalTimeSpentDead": 89,
                "totalUnitsHealed": 2,
                "tripleKills": 0,
                "trueDamageDealt": 13026,
                "trueDamageDealtToChampions": 2543,
                "trueDamageTaken": 592,
                "turretKills": 4,
                "turretsLost": 5,
                "unrealKills": 0,
                "visionScore": 10,
                "visionWardsBoughtInGame": 0,
                "wardsKilled": 6,
                "wardsPlaced": 5,
                "win": true
            },
            {
                "assists": 20,
                "baronKills": 0,
                "bountyLevel": 0,
                "champExperience": 11841,
                "champLevel": 14,
                "championId": 89,
                "championName": "Leona",
                "championTransform": 0,
                "consumablesPurchased": 9,
                "damageDealtToBuildings": 652,
                "damageDealtToObjectives": 3575,
                "damageDealtToTurrets": 652,
                "damageSelfMitigated": 22465,
                "deaths": 4,
                "detectorWardsPlaced": 5,
                "doubleKills": 0,
                "dragonKills": 0,
                "firstBloodAssist": true,
                "firstBloodKill": false,
                "firstTowerAssist": false,
                "firstTowerKill": false,
                "gameEndedInEarlySurrender": false,
                "gameEndedInSurrender": false,
                "goldEarned": 9387,
                "goldSpent": 9375,
                "individualPosition": "UTILITY",
                "inhibitorKills": 0,
                "inhibitorsLost": 0,
                "item0": 3190,
                "item1": 2055,
                "item2": 3860,
                "item3": 3050,
                "item4": 3117,
                "item5": 3109,
                "item6": 3364,
                "itemsPurchased": 23,
                "killingSprees": 1,
                "kills": 4,
                "lane": "BOTTOM",
                "largestCriticalStrike": 0,
                "largestKillingSpree": 2,
                "largestMultiKill": 1,
                "longestTimeSpentLiving": 633,
                "magicDamageDealt": 9099,
                "magicDamageDealtToChampions": 4767,
                "magicDamageTaken": 8550,
                "neutralMinionsKilled": 0,
                "nexusKills": 0,
                "nexusLost": 0,
                "objectivesStolen": 0,
                "objectivesStolenAssists": 0,
                "participantId": 5,
                "pentaKills": 0,
                "perks": {
                    "statPerks": {
                        "defense": 5002,
                        "flex": 5002,
                        "offense": 5007
                    },
                    "styles": [
                        {
                            "description": "primaryStyle",
                            "selections": [
                                {
                                    "perk": 8439,
                                    "var1": 963,
                                    "var2": 0,
                                    "var3": 0
                                },
                                {
                                    "perk": 8463,
                                    "var1": 1655,
                                    "var2": 0,
                                    "var3": 0
                                },
                                {
                                    "perk": 8473,
                                    "var1": 480,
                                    "var2": 0,
                                    "var3": 0
                                },
                                {
                                    "perk": 8451,
                                    "var1": 185,
                                    "var2": 0,
                                    "var3": 0
                                }
                            ],
                            "style": 8400
                        },
                        {
                            "description": "subStyle",
                            "selections": [
                                {
                                    "perk": 8306,
                                    "var1": 3,
                                    "var2": 0,
                                    "var3": 0
                                },
                                {
                                    "perk": 8347,
                                    "var1": 0,
                                    "var2": 0,
                                    "var3": 0
                                }
                            ],
                            "style": 8300
                        }
                    ]
                },
                "physicalDamageDealt": 8877,
                "physicalDamageDealtToChampions": 2902,
                "physicalDamageTaken": 11183,
                "profileIcon": 4896,
                "puuid": "CMOQyxto9pp0_IpgEVHARRSMaytCOBZHm6Bjkkl0xnl5zDQXsOSAt88M7Rnsy5NFL4RwanE6RQYwdg",
                "quadraKills": 0,
                "riotIdName": "",
                "riotIdTagline": "",
                "role": "SUPPORT",
                "sightWardsBoughtInGame": 0,
                "spell1Casts": 62,
                "spell2Casts": 28,
                "spell3Casts": 28,
                "spell4Casts": 12,
                "summoner1Casts": 8,
                "summoner1Id": 14,
                "summoner2Casts": 7,
                "summoner2Id": 4,
                "summonerId": "RWU8KriSI6lsT6nMAeTXinudKS1nXL7gUW21aosrxY95yg",
                "summonerLevel": 294,
                "summonerName": "아이스 모찌",
                "teamEarlySurrendered": false,
                "teamId": 100,
                "teamPosition": "UTILITY",
                "timeCCingOthers": 51,
                "timePlayed": 1698,
                "totalDamageDealt": 26563,
                "totalDamageDealtToChampions": 8699,
                "totalDamageShieldedOnTeammates": 861,
                "totalDamageTaken": 20085,
                "totalHeal": 2061,
                "totalHealsOnTeammates": 724,
                "totalMinionsKilled": 47,
                "totalTimeCCDealt": 98,
                "totalTimeSpentDead": 83,
                "totalUnitsHealed": 5,
                "tripleKills": 0,
                "trueDamageDealt": 8587,
                "trueDamageDealtToChampions": 1030,
                "trueDamageTaken": 351,
                "turretKills": 0,
                "turretsLost": 5,
                "unrealKills": 0,
                "visionScore": 65,
                "visionWardsBoughtInGame": 7,
                "wardsKilled": 11,
                "wardsPlaced": 25,
                "win": true
            },
            {
                "assists": 7,
                "baronKills": 0,
                "bountyLevel": 0,
                "champExperience": 13576,
                "champLevel": 15,
                "championId": 39,
                "championName": "Irelia",
                "championTransform": 0,
                "consumablesPurchased": 4,
                "damageDealtToBuildings": 4529,
                "damageDealtToObjectives": 5927,
                "damageDealtToTurrets": 4529,
                "damageSelfMitigated": 22442,
                "deaths": 16,
                "detectorWardsPlaced": 0,
                "doubleKills": 0,
                "dragonKills": 0,
                "firstBloodAssist": false,
                "firstBloodKill": false,
                "firstTowerAssist": false,
                "firstTowerKill": false,
                "gameEndedInEarlySurrender": false,
                "gameEndedInSurrender": false,
                "goldEarned": 10742,
                "goldSpent": 11160,
                "individualPosition": "TOP",
                "inhibitorKills": 0,
                "inhibitorsLost": 1,
                "item0": 3051,
                "item1": 6673,
                "item2": 1057,
                "item3": 0,
                "item4": 3153,
                "item5": 3111,
                "item6": 3340,
                "itemsPurchased": 25,
                "killingSprees": 0,
                "kills": 4,
                "lane": "TOP",
                "largestCriticalStrike": 406,
                "largestKillingSpree": 0,
                "largestMultiKill": 1,
                "longestTimeSpentLiving": 182,
                "magicDamageDealt": 13528,
                "magicDamageDealtToChampions": 4634,
                "magicDamageTaken": 21991,
                "neutralMinionsKilled": 3,
                "nexusKills": 0,
                "nexusLost": 1,
                "objectivesStolen": 0,
                "objectivesStolenAssists": 0,
                "participantId": 6,
                "pentaKills": 0,
                "perks": {
                    "statPerks": {
                        "defense": 5002,
                        "flex": 5008,
                        "offense": 5005
                    },
                    "styles": [
                        {
                            "description": "primaryStyle",
                            "selections": [
                                {
                                    "perk": 8010,
                                    "var1": 283,
                                    "var2": 0,
                                    "var3": 0
                                },
                                {
                                    "perk": 8009,
                                    "var1": 1347,
                                    "var2": 0,
                                    "var3": 0
                                },
                                {
                                    "perk": 9103,
                                    "var1": 25,
                                    "var2": 50,
                                    "var3": 0
                                },
                                {
                                    "perk": 8299,
                                    "var1": 727,
                                    "var2": 0,
                                    "var3": 0
                                }
                            ],
                            "style": 8000
                        },
                        {
                            "description": "subStyle",
                            "selections": [
                                {
                                    "perk": 8143,
                                    "var1": 520,
                                    "var2": 0,
                                    "var3": 0
                                },
                                {
                                    "perk": 8135,
                                    "var1": 0,
                                    "var2": 4,
                                    "var3": 0
                                }
                            ],
                            "style": 8100
                        }
                    ]
                },
                "physicalDamageDealt": 119020,
                "physicalDamageDealtToChampions": 12036,
                "physicalDamageTaken": 11284,
                "profileIcon": 4631,
                "puuid": "anhO2QehkXHiEYoLJ35K2C3cRI_8P3IhxcQd5RPR60ZvjNSOAs8jAy2Ou53oNzoVuqbrmipMcTZsOw",
                "quadraKills": 0,
                "riotIdName": "",
                "riotIdTagline": "",
                "role": "SOLO",
                "sightWardsBoughtInGame": 0,
                "spell1Casts": 234,
                "spell2Casts": 24,
                "spell3Casts": 58,
                "spell4Casts": 7,
                "summoner1Casts": 2,
                "summoner1Id": 12,
                "summoner2Casts": 4,
                "summoner2Id": 4,
                "summonerId": "eh11LOHHcQUpQSZV-uCPdxNN6V5f3vBCx7uw4RM_-92rVnVfPOJ-ZtvKww",
                "summonerLevel": 39,
                "summonerName": "소년가장 손인욱",
                "teamEarlySurrendered": false,
                "teamId": 200,
                "teamPosition": "TOP",
                "timeCCingOthers": 12,
                "timePlayed": 1698,
                "totalDamageDealt": 140958,
                "totalDamageDealtToChampions": 16671,
                "totalDamageShieldedOnTeammates": 0,
                "totalDamageTaken": 35500,
                "totalHeal": 2246,
                "totalHealsOnTeammates": 0,
                "totalMinionsKilled": 196,
                "totalTimeCCDealt": 40,
                "totalTimeSpentDead": 428,
                "totalUnitsHealed": 1,
                "tripleKills": 0,
                "trueDamageDealt": 8410,
                "trueDamageDealtToChampions": 0,
                "trueDamageTaken": 2224,
                "turretKills": 2,
                "turretsLost": 8,
                "unrealKills": 0,
                "visionScore": 13,
                "visionWardsBoughtInGame": 0,
                "wardsKilled": 0,
                "wardsPlaced": 9,
                "win": false
            },
            {
                "assists": 8,
                "baronKills": 0,
                "bountyLevel": 0,
                "champExperience": 13364,
                "champLevel": 15,
                "championId": 60,
                "championName": "Elise",
                "championTransform": 0,
                "consumablesPurchased": 5,
                "damageDealtToBuildings": 167,
                "damageDealtToObjectives": 22241,
                "damageDealtToTurrets": 167,
                "damageSelfMitigated": 10287,
                "deaths": 5,
                "detectorWardsPlaced": 5,
                "doubleKills": 1,
                "dragonKills": 2,
                "firstBloodAssist": false,
                "firstBloodKill": false,
                "firstTowerAssist": false,
                "firstTowerKill": false,
                "gameEndedInEarlySurrender": false,
                "gameEndedInSurrender": false,
                "goldEarned": 13445,
                "goldSpent": 12925,
                "individualPosition": "JUNGLE",
                "inhibitorKills": 0,
                "inhibitorsLost": 1,
                "item0": 3157,
                "item1": 3135,
                "item2": 1026,
                "item3": 3041,
                "item4": 3020,
                "item5": 4636,
                "item6": 3364,
                "itemsPurchased": 25,
                "killingSprees": 3,
                "kills": 12,
                "lane": "JUNGLE",
                "largestCriticalStrike": 0,
                "largestKillingSpree": 7,
                "largestMultiKill": 2,
                "longestTimeSpentLiving": 855,
                "magicDamageDealt": 97095,
                "magicDamageDealtToChampions": 21497,
                "magicDamageTaken": 10866,
                "neutralMinionsKilled": 112,
                "nexusKills": 0,
                "nexusLost": 1,
                "objectivesStolen": 0,
                "objectivesStolenAssists": 0,
                "participantId": 7,
                "pentaKills": 0,
                "perks": {
                    "statPerks": {
                        "defense": 5003,
                        "flex": 5008,
                        "offense": 5005
                    },
                    "styles": [
                        {
                            "description": "primaryStyle",
                            "selections": [
                                {
                                    "perk": 8005,
                                    "var1": 1004,
                                    "var2": 858,
                                    "var3": 145
                                },
                                {
                                    "perk": 9111,
                                    "var1": 866,
                                    "var2": 400,
                                    "var3": 0
                                },
                                {
                                    "perk": 9104,
                                    "var1": 10,
                                    "var2": 0,
                                    "var3": 0
                                },
                                {
                                    "perk": 8014,
                                    "var1": 486,
                                    "var2": 0,
                                    "var3": 0
                                }
                            ],
                            "style": 8000
                        },
                        {
                            "description": "subStyle",
                            "selections": [
                                {
                                    "perk": 8138,
                                    "var1": 30,
                                    "var2": 0,
                                    "var3": 0
                                },
                                {
                                    "perk": 8105,
                                    "var1": 13,
                                    "var2": 5,
                                    "var3": 0
                                }
                            ],
                            "style": 8100
                        }
                    ]
                },
                "physicalDamageDealt": 18625,
                "physicalDamageDealtToChampions": 1298,
                "physicalDamageTaken": 12522,
                "profileIcon": 4904,
                "puuid": "k2Gcv83OOAUzNH9ZbvyWFEaQJi1GPQRRfu77RH3v8G41YyujAYTmr6_GbYInhy7g3y0QgUJWkoxkSg",
                "quadraKills": 0,
                "riotIdName": "",
                "riotIdTagline": "",
                "role": "NONE",
                "sightWardsBoughtInGame": 0,
                "spell1Casts": 155,
                "spell2Casts": 169,
                "spell3Casts": 60,
                "spell4Casts": 180,
                "summoner1Casts": 16,
                "summoner1Id": 11,
                "summoner2Casts": 3,
                "summoner2Id": 4,
                "summonerId": "n3IclTl1DJmp8ri0eT9lL6scNPyph2F1MfHxfactDlSpGQ",
                "summonerLevel": 279,
                "summonerName": "한국부동산원",
                "teamEarlySurrendered": false,
                "teamId": 200,
                "teamPosition": "JUNGLE",
                "timeCCingOthers": 30,
                "timePlayed": 1698,
                "totalDamageDealt": 125643,
                "totalDamageDealtToChampions": 24068,
                "totalDamageShieldedOnTeammates": 0,
                "totalDamageTaken": 24057,
                "totalHeal": 9513,
                "totalHealsOnTeammates": 0,
                "totalMinionsKilled": 29,
                "totalTimeCCDealt": 136,
                "totalTimeSpentDead": 212,
                "totalUnitsHealed": 1,
                "tripleKills": 0,
                "trueDamageDealt": 9922,
                "trueDamageDealtToChampions": 1272,
                "trueDamageTaken": 669,
                "turretKills": 1,
                "turretsLost": 8,
                "unrealKills": 0,
                "visionScore": 40,
                "visionWardsBoughtInGame": 5,
                "wardsKilled": 10,
                "wardsPlaced": 6,
                "win": false
            },
            {
                "assists": 7,
                "baronKills": 0,
                "bountyLevel": 0,
                "champExperience": 13885,
                "champLevel": 15,
                "championId": 126,
                "championName": "Jayce",
                "championTransform": 0,
                "consumablesPurchased": 2,
                "damageDealtToBuildings": 2470,
                "damageDealtToObjectives": 10037,
                "damageDealtToTurrets": 2470,
                "damageSelfMitigated": 19323,
                "deaths": 4,
                "detectorWardsPlaced": 2,
                "doubleKills": 1,
                "dragonKills": 0,
                "firstBloodAssist": false,
                "firstBloodKill": false,
                "firstTowerAssist": false,
                "firstTowerKill": false,
                "gameEndedInEarlySurrender": false,
                "gameEndedInSurrender": false,
                "goldEarned": 12222,
                "goldSpent": 11225,
                "individualPosition": "MIDDLE",
                "inhibitorKills": 0,
                "inhibitorsLost": 1,
                "item0": 2033,
                "item1": 3111,
                "item2": 6692,
                "item3": 3156,
                "item4": 3042,
                "item5": 1037,
                "item6": 3364,
                "itemsPurchased": 20,
                "killingSprees": 2,
                "kills": 6,
                "lane": "JUNGLE",
                "largestCriticalStrike": 0,
                "largestKillingSpree": 4,
                "largestMultiKill": 2,
                "longestTimeSpentLiving": 1238,
                "magicDamageDealt": 13095,
                "magicDamageDealtToChampions": 2670,
                "magicDamageTaken": 11038,
                "neutralMinionsKilled": 12,
                "nexusKills": 0,
                "nexusLost": 1,
                "objectivesStolen": 0,
                "objectivesStolenAssists": 0,
                "participantId": 8,
                "pentaKills": 0,
                "perks": {
                    "statPerks": {
                        "defense": 5003,
                        "flex": 5008,
                        "offense": 5008
                    },
                    "styles": [
                        {
                            "description": "primaryStyle",
                            "selections": [
                                {
                                    "perk": 8230,
                                    "var1": 8,
                                    "var2": 0,
                                    "var3": 0
                                },
                                {
                                    "perk": 8224,
                                    "var1": 621,
                                    "var2": 0,
                                    "var3": 0
                                },
                                {
                                    "perk": 8210,
                                    "var1": 19,
                                    "var2": 0,
                                    "var3": 0
                                },
                                {
                                    "perk": 8236,
                                    "var1": 14,
                                    "var2": 0,
                                    "var3": 0
                                }
                            ],
                            "style": 8200
                        },
                        {
                            "description": "subStyle",
                            "selections": [
                                {
                                    "perk": 8345,
                                    "var1": 3,
                                    "var2": 0,
                                    "var3": 0
                                },
                                {
                                    "perk": 8304,
                                    "var1": 11,
                                    "var2": 1,
                                    "var3": 5
                                }
                            ],
                            "style": 8300
                        }
                    ]
                },
                "physicalDamageDealt": 122460,
                "physicalDamageDealtToChampions": 13572,
                "physicalDamageTaken": 5058,
                "profileIcon": 4905,
                "puuid": "DYsLx6LBCXy2rGkxBHuMVLfpXIFPu9laxRCKQdSHVKpvibW6SjvrPszVg08hVH0YJayl_Q-XxVUWOA",
                "quadraKills": 0,
                "riotIdName": "",
                "riotIdTagline": "",
                "role": "NONE",
                "sightWardsBoughtInGame": 0,
                "spell1Casts": 120,
                "spell2Casts": 71,
                "spell3Casts": 80,
                "spell4Casts": 130,
                "summoner1Casts": 3,
                "summoner1Id": 12,
                "summoner2Casts": 4,
                "summoner2Id": 4,
                "summonerId": "Bs26eN4RgyDKMIuQuI5CCLG6wqIdQN6kO4DwZKQcbYMHThg",
                "summonerLevel": 44,
                "summonerName": "망둥킹",
                "teamEarlySurrendered": false,
                "teamId": 200,
                "teamPosition": "MIDDLE",
                "timeCCingOthers": 6,
                "timePlayed": 1698,
                "totalDamageDealt": 140490,
                "totalDamageDealtToChampions": 16435,
                "totalDamageShieldedOnTeammates": 0,
                "totalDamageTaken": 16422,
                "totalHeal": 399,
                "totalHealsOnTeammates": 0,
                "totalMinionsKilled": 188,
                "totalTimeCCDealt": 112,
                "totalTimeSpentDead": 127,
                "totalUnitsHealed": 1,
                "tripleKills": 0,
                "trueDamageDealt": 4934,
                "trueDamageDealtToChampions": 192,
                "trueDamageTaken": 325,
                "turretKills": 1,
                "turretsLost": 8,
                "unrealKills": 0,
                "visionScore": 25,
                "visionWardsBoughtInGame": 2,
                "wardsKilled": 4,
                "wardsPlaced": 8,
                "win": false
            },
            {
                "assists": 6,
                "baronKills": 0,
                "bountyLevel": 1,
                "champExperience": 11663,
                "champLevel": 14,
                "championId": 202,
                "championName": "Jhin",
                "championTransform": 0,
                "consumablesPurchased": 4,
                "damageDealtToBuildings": 2022,
                "damageDealtToObjectives": 8387,
                "damageDealtToTurrets": 2022,
                "damageSelfMitigated": 5586,
                "deaths": 7,
                "detectorWardsPlaced": 2,
                "doubleKills": 1,
                "dragonKills": 0,
                "firstBloodAssist": false,
                "firstBloodKill": false,
                "firstTowerAssist": false,
                "firstTowerKill": false,
                "gameEndedInEarlySurrender": false,
                "gameEndedInSurrender": false,
                "goldEarned": 11178,
                "goldSpent": 10625,
                "individualPosition": "BOTTOM",
                "inhibitorKills": 0,
                "inhibitorsLost": 1,
                "item0": 3094,
                "item1": 3031,
                "item2": 0,
                "item3": 6671,
                "item4": 2055,
                "item5": 3009,
                "item6": 3363,
                "itemsPurchased": 19,
                "killingSprees": 1,
                "kills": 6,
                "lane": "BOTTOM",
                "largestCriticalStrike": 1021,
                "largestKillingSpree": 3,
                "largestMultiKill": 3,
                "longestTimeSpentLiving": 597,
                "magicDamageDealt": 7731,
                "magicDamageDealtToChampions": 2360,
                "magicDamageTaken": 8092,
                "neutralMinionsKilled": 8,
                "nexusKills": 0,
                "nexusLost": 1,
                "objectivesStolen": 0,
                "objectivesStolenAssists": 0,
                "participantId": 9,
                "pentaKills": 0,
                "perks": {
                    "statPerks": {
                        "defense": 5002,
                        "flex": 5008,
                        "offense": 5008
                    },
                    "styles": [
                        {
                            "description": "primaryStyle",
                            "selections": [
                                {
                                    "perk": 8021,
                                    "var1": 884,
                                    "var2": 0,
                                    "var3": 0
                                },
                                {
                                    "perk": 8009,
                                    "var1": 1262,
                                    "var2": 0,
                                    "var3": 0
                                },
                                {
                                    "perk": 9103,
                                    "var1": 22,
                                    "var2": 40,
                                    "var3": 0
                                },
                                {
                                    "perk": 8017,
                                    "var1": 553,
                                    "var2": 0,
                                    "var3": 0
                                }
                            ],
                            "style": 8000
                        },
                        {
                            "description": "subStyle",
                            "selections": [
                                {
                                    "perk": 8304,
                                    "var1": 10,
                                    "var2": 3,
                                    "var3": 0
                                },
                                {
                                    "perk": 8345,
                                    "var1": 3,
                                    "var2": 0,
                                    "var3": 0
                                }
                            ],
                            "style": 8300
                        }
                    ]
                },
                "physicalDamageDealt": 101867,
                "physicalDamageDealtToChampions": 8606,
                "physicalDamageTaken": 6914,
                "profileIcon": 4760,
                "puuid": "CiqgoKTY6Jb5gmYdo40KpXpH6zA6TunRnAdSvEDcbIJSwGHmCAB-IVyZ83CHIy-udMuVqdiw6Jk8Zw",
                "quadraKills": 0,
                "riotIdName": "",
                "riotIdTagline": "",
                "role": "CARRY",
                "sightWardsBoughtInGame": 0,
                "spell1Casts": 65,
                "spell2Casts": 30,
                "spell3Casts": 16,
                "spell4Casts": 11,
                "summoner1Casts": 5,
                "summoner1Id": 7,
                "summoner2Casts": 4,
                "summoner2Id": 4,
                "summonerId": "S2kL__e_ssXbHztIhxlf1vWz2FTxGxBBhyM-Y2tvxzaVKKs",
                "summonerLevel": 207,
                "summonerName": "하설님",
                "teamEarlySurrendered": false,
                "teamId": 200,
                "teamPosition": "BOTTOM",
                "timeCCingOthers": 17,
                "timePlayed": 1698,
                "totalDamageDealt": 111694,
                "totalDamageDealtToChampions": 11046,
                "totalDamageShieldedOnTeammates": 0,
                "totalDamageTaken": 15961,
                "totalHeal": 2846,
                "totalHealsOnTeammates": 560,
                "totalMinionsKilled": 170,
                "totalTimeCCDealt": 100,
                "totalTimeSpentDead": 161,
                "totalUnitsHealed": 3,
                "tripleKills": 1,
                "trueDamageDealt": 2095,
                "trueDamageDealtToChampions": 80,
                "trueDamageTaken": 955,
                "turretKills": 1,
                "turretsLost": 8,
                "unrealKills": 0,
                "visionScore": 21,
                "visionWardsBoughtInGame": 3,
                "wardsKilled": 4,
                "wardsPlaced": 9,
                "win": false
            },
            {
                "assists": 10,
                "baronKills": 0,
                "bountyLevel": 0,
                "champExperience": 9787,
                "champLevel": 12,
                "championId": 111,
                "championName": "Nautilus",
                "championTransform": 0,
                "consumablesPurchased": 10,
                "damageDealtToBuildings": 225,
                "damageDealtToObjectives": 370,
                "damageDealtToTurrets": 225,
                "damageSelfMitigated": 29811,
                "deaths": 11,
                "detectorWardsPlaced": 8,
                "doubleKills": 0,
                "dragonKills": 0,
                "firstBloodAssist": false,
                "firstBloodKill": false,
                "firstTowerAssist": false,
                "firstTowerKill": false,
                "gameEndedInEarlySurrender": false,
                "gameEndedInSurrender": false,
                "goldEarned": 6728,
                "goldSpent": 5650,
                "individualPosition": "UTILITY",
                "inhibitorKills": 0,
                "inhibitorsLost": 1,
                "item0": 3190,
                "item1": 2031,
                "item2": 3860,
                "item3": 3801,
                "item4": 1006,
                "item5": 3111,
                "item6": 3364,
                "itemsPurchased": 25,
                "killingSprees": 0,
                "kills": 1,
                "lane": "BOTTOM",
                "largestCriticalStrike": 0,
                "largestKillingSpree": 0,
                "largestMultiKill": 1,
                "longestTimeSpentLiving": 314,
                "magicDamageDealt": 8911,
                "magicDamageDealtToChampions": 4954,
                "magicDamageTaken": 12719,
                "neutralMinionsKilled": 4,
                "nexusKills": 0,
                "nexusLost": 1,
                "objectivesStolen": 0,
                "objectivesStolenAssists": 0,
                "participantId": 10,
                "pentaKills": 0,
                "perks": {
                    "statPerks": {
                        "defense": 5002,
                        "flex": 5002,
                        "offense": 5007
                    },
                    "styles": [
                        {
                            "description": "primaryStyle",
                            "selections": [
                                {
                                    "perk": 8439,
                                    "var1": 565,
                                    "var2": 0,
                                    "var3": 0
                                },
                                {
                                    "perk": 8401,
                                    "var1": 360,
                                    "var2": 0,
                                    "var3": 0
                                },
                                {
                                    "perk": 8444,
                                    "var1": 950,
                                    "var2": 0,
                                    "var3": 0
                                },
                                {
                                    "perk": 8453,
                                    "var1": 230,
                                    "var2": 675,
                                    "var3": 0
                                }
                            ],
                            "style": 8400
                        },
                        {
                            "description": "subStyle",
                            "selections": [
                                {
                                    "perk": 8345,
                                    "var1": 3,
                                    "var2": 0,
                                    "var3": 0
                                },
                                {
                                    "perk": 8352,
                                    "var1": 108,
                                    "var2": 928,
                                    "var3": 19
                                }
                            ],
                            "style": 8300
                        }
                    ]
                },
                "physicalDamageDealt": 7589,
                "physicalDamageDealtToChampions": 1956,
                "physicalDamageTaken": 10880,
                "profileIcon": 3791,
                "puuid": "R4-izM141yZx6eFehD0c9mGIVU_Csyk5Hsj8ITZAT8sarJ9tA7npf1nQ4Kra5yCy4gadj9zR8DToQw",
                "quadraKills": 0,
                "riotIdName": "",
                "riotIdTagline": "",
                "role": "SUPPORT",
                "sightWardsBoughtInGame": 0,
                "spell1Casts": 66,
                "spell2Casts": 37,
                "spell3Casts": 21,
                "spell4Casts": 8,
                "summoner1Casts": 4,
                "summoner1Id": 14,
                "summoner2Casts": 5,
                "summoner2Id": 4,
                "summonerId": "pEatrP8VceH7Iej_SD0K6vFoluz-njWxSOLHzO1ZBXFBJo0",
                "summonerLevel": 210,
                "summonerName": "소떡소떡충",
                "teamEarlySurrendered": false,
                "teamId": 200,
                "teamPosition": "UTILITY",
                "timeCCingOthers": 53,
                "timePlayed": 1698,
                "totalDamageDealt": 22108,
                "totalDamageDealtToChampions": 7546,
                "totalDamageShieldedOnTeammates": 774,
                "totalDamageTaken": 24772,
                "totalHeal": 1145,
                "totalHealsOnTeammates": 0,
                "totalMinionsKilled": 32,
                "totalTimeCCDealt": 200,
                "totalTimeSpentDead": 254,
                "totalUnitsHealed": 1,
                "tripleKills": 0,
                "trueDamageDealt": 5608,
                "trueDamageDealtToChampions": 635,
                "trueDamageTaken": 1172,
                "turretKills": 0,
                "turretsLost": 8,
                "unrealKills": 0,
                "visionScore": 48,
                "visionWardsBoughtInGame": 8,
                "wardsKilled": 5,
                "wardsPlaced": 26,
                "win": false
            }
        ],
        "platformId": "KR",
        "queueId": 420,
        "teams": [
            {
                "bans": [
                    {
                        "championId": 526,
                        "pickTurn": 1
                    },
                    {
                        "championId": 25,
                        "pickTurn": 2
                    },
                    {
                        "championId": 105,
                        "pickTurn": 3
                    },
                    {
                        "championId": 58,
                        "pickTurn": 4
                    },
                    {
                        "championId": 517,
                        "pickTurn": 5
                    }
                ],
                "objectives": {
                    "baron": {
                        "first": true,
                        "kills": 1
                    },
                    "champion": {
                        "first": true,
                        "kills": 43
                    },
                    "dragon": {
                        "first": false,
                        "kills": 2
                    },
                    "inhibitor": {
                        "first": true,
                        "kills": 1
                    },
                    "riftHerald": {
                        "first": false,
                        "kills": 0
                    },
                    "tower": {
                        "first": true,
                        "kills": 8
                    }
                },
                "teamId": 100,
                "win": true
            },
            {
                "bans": [
                    {
                        "championId": 35,
                        "pickTurn": 6
                    },
                    {
                        "championId": 13,
                        "pickTurn": 7
                    },
                    {
                        "championId": 360,
                        "pickTurn": 8
                    },
                    {
                        "championId": 142,
                        "pickTurn": 9
                    },
                    {
                        "championId": 122,
                        "pickTurn": 10
                    }
                ],
                "objectives": {
                    "baron": {
                        "first": false,
                        "kills": 0
                    },
                    "champion": {
                        "first": false,
                        "kills": 29
                    },
                    "dragon": {
                        "first": true,
                        "kills": 2
                    },
                    "inhibitor": {
                        "first": false,
                        "kills": 0
                    },
                    "riftHerald": {
                        "first": true,
                        "kills": 2
                    },
                    "tower": {
                        "first": false,
                        "kills": 5
                    }
                },
                "teamId": 200,
                "win": false
            }
        ]
    }
}